st_text_input_dnd_sortable/__init__.py
st_text_input_dnd_sortable/frontend/build/asset-manifest.json
st_text_input_dnd_sortable/frontend/build/bootstrap.min.css
st_text_input_dnd_sortable/frontend/build/index.html
st_text_input_dnd_sortable/frontend/build/static/css/main.9f2f424c.css
st_text_input_dnd_sortable/frontend/build/static/css/main.9f2f424c.css.map
st_text_input_dnd_sortable/frontend/build/static/css/main.abd4a1e0.css
st_text_input_dnd_sortable/frontend/build/static/css/main.abd4a1e0.css.map
st_text_input_dnd_sortable/frontend/build/static/js/main.eee975f9.js
st_text_input_dnd_sortable/frontend/build/static/js/main.eee975f9.js.LICENSE.txt
st_text_input_dnd_sortable/frontend/build/static/js/main.eee975f9.js.map
st_text_input_dnd_sortable-0.0.5.dist-info/LICENSE
st_text_input_dnd_sortable-0.0.5.dist-info/METADATA
st_text_input_dnd_sortable-0.0.5.dist-info/WHEEL
st_text_input_dnd_sortable-0.0.5.dist-info/top_level.txt
st_text_input_dnd_sortable-0.0.5.dist-info/RECORD
