Metadata-Version: 2.1
Name: st-text-input-dnd-sortable
Version: 0.0.5
Summary: Streamlit component which include row(s) of text input field with DnD property
Home-page: 
Author: jchattarin
Author-email: chattarin2000@gmail.com
Requires-Python: >=3.8
License-File: LICENSE
Requires-Dist: streamlit (>=0.63)
